stpredictions/__init__.py
stpredictions/datasets/__init__.py
stpredictions/datasets/load_data.py
stpredictions/datasets/bibtex/bibtex-test.arff
stpredictions/datasets/bibtex/bibtex-train.arff
stpredictions/datasets/bibtex/bibtex.arff
stpredictions/datasets/bibtex/bibtex.xml
stpredictions/datasets/bookmarks/bookmarks.xml
stpredictions/datasets/corel5k/Corel5k-test.arff
stpredictions/datasets/corel5k/Corel5k-train.arff
stpredictions/datasets/corel5k/Corel5k.arff
stpredictions/datasets/corel5k/Corel5k.xml
stpredictions/datasets/usps/usps.h5
stpredictions/helpers/__init__.py
stpredictions/helpers/openmp_helpers.py
stpredictions/helpers/pre_build_helpers.py
stpredictions/metrics/__init__.py
stpredictions/metrics/loss.py
stpredictions/models/__init__.py
stpredictions/models/DIOKR/IOKR.py
stpredictions/models/DIOKR/__init__.py
stpredictions/models/DIOKR/cost.py
stpredictions/models/DIOKR/estimator.py
stpredictions/models/DIOKR/kernel.py
stpredictions/models/DIOKR/net.py
stpredictions/models/DIOKR/utils.py
stpredictions/models/IOKR/Sketch.py
stpredictions/models/IOKR/SketchedIOKR.py
stpredictions/models/IOKR/__init__.py
stpredictions/models/IOKR/model.py
stpredictions/models/IOKR/utils.py
stpredictions/models/OK3/__init__.py
stpredictions/models/OK3/_classes.py
stpredictions/models/OK3/_criterion.c
stpredictions/models/OK3/_criterion.cpython-39-darwin.so
stpredictions/models/OK3/_forest.py
stpredictions/models/OK3/_quad_tree.c
stpredictions/models/OK3/_quad_tree.cpython-39-darwin.so
stpredictions/models/OK3/_random.c
stpredictions/models/OK3/_random.cpython-39-darwin.so
stpredictions/models/OK3/_splitter.c
stpredictions/models/OK3/_splitter.cpython-39-darwin.so
stpredictions/models/OK3/_tree.c
stpredictions/models/OK3/_tree.cpython-39-darwin.so
stpredictions/models/OK3/_utils.c
stpredictions/models/OK3/_utils.cpython-39-darwin.so
stpredictions/models/OK3/base.py
stpredictions/models/OK3/kernel.py
stpredictions/models/OK3/structured_object.py
stpredictions/viz/__init__.py
structured_predictions-0.1.3.dist-info/LICENSE
structured_predictions-0.1.3.dist-info/METADATA
structured_predictions-0.1.3.dist-info/WHEEL
structured_predictions-0.1.3.dist-info/top_level.txt
structured_predictions-0.1.3.dist-info/RECORD
