Metadata-Version: 2.1
Name: structured-predictions
Version: 0.1.3
Summary: Structured-Predictions
Home-page: https://github.com/hi-paris/structured-predictions
Author: Florence d'Alché-Buc (Researcher), Luc Motte (Researcher), Tamim El Ahmad (Researcher) , Awais Sani (Engineer), Danaël  Schlewer-Becker(Engineer), Gaëtan Brison (Engineer)
Author-email: structured-predictions@gmail.com
License: MIT
Platform: linux
Platform: macosx
Platform: windows
Classifier: Development Status :: 5 - Production/Stable
Classifier: Intended Audience :: Developers
Classifier: Intended Audience :: Education
Classifier: Intended Audience :: Science/Research
Classifier: License :: OSI Approved :: MIT License
Classifier: Environment :: Console
Classifier: Operating System :: OS Independent
Classifier: Operating System :: POSIX :: Linux
Classifier: Operating System :: MacOS
Classifier: Operating System :: POSIX
Classifier: Operating System :: Microsoft :: Windows
Classifier: Programming Language :: Python
Classifier: Programming Language :: Cython
Classifier: Topic :: Utilities
Classifier: Topic :: Scientific/Engineering :: Artificial Intelligence
Classifier: Topic :: Scientific/Engineering :: Mathematics
Classifier: Topic :: Scientific/Engineering :: Information Analysis
Classifier: Programming Language :: Python :: 3
Classifier: Programming Language :: Python :: 3.8
Classifier: Programming Language :: Python :: 3.9
Classifier: Programming Language :: Python :: 3.10
Requires-Python: >=3.6
License-File: LICENSE
Requires-Dist: numpy >=1.16
Requires-Dist: scipy >=1.0
Requires-Dist: scikit-learn
Requires-Dist: torch
Requires-Dist: liac-arff
Requires-Dist: requests
